{
    "data": [
             {
             "startData":
             {
             "chaPos1":201,
             "chaPos2":206,
             "chaPos3":205,
             "chaPos4":206,
             "chaPos5":209,
             "chaPos6":202
             },
             "name":"奉招破大辽1",
             "coin":8500,
             "xp":850,
             "type":1,
             "chalevel":85,
             "card":-1,
             "sword":-1
             },
             {
             "startData":
             {
             "chaPos1":208,
             "chaPos2":203,
             "chaPos3":204,
             "chaPos4":209,
             "chaPos5":205,
             "chaPos6":202
             },
             "name":"奉招破大辽2",
             "coin":8600,
             "xp":860,
             "type":1,
             "chalevel":86,
             "card":-1,
             "sword":-1
             },
             {
             "startData":
             {
             "chaPos1":208,
             "chaPos2":207,
             "chaPos3":210,
             "chaPos4":206,
             "chaPos5":204,
             "chaPos6":207
             },
             "name":"大奉招破大辽3",
             "coin":8600,
             "xp":870,
             "type":1,
             "chalevel":87,
             "card":-1,
             "sword":805001
             },
             {
             "startData":
             {
             "chaPos1":207,
             "chaPos2":206,
             "chaPos3":205,
             "chaPos4":207,
             "chaPos5":209,
             "chaPos6":204
             },
             "name":"兵打蓟州城1",
             "coin":8700,
             "xp":870,
             "type":1,
             "chalevel":88,
             "card":-1,
             "sword":-1
             },
             {
             "startData":
             {
             "chaPos1":205,
             "chaPos2":206,
             "chaPos3":204,
             "chaPos4":207,
             "chaPos5":209,
             "chaPos6":208
             },
             "name":"兵打蓟州城2",
             "coin":8700,
             "xp":870,
             "type":1,
             "chalevel":87,
             "card":-1,
             "sword":701001
             },
             {
             "startData":
             {
             "chaPos1":207,
             "chaPos2":206,
             "chaPos3":204,
             "chaPos4":208,
             "chaPos5":210,
             "chaPos6":203
             },
             "name":"兵打蓟州城3",
             "coin":8700,
             "xp":870,
             "type":1,
             "chalevel":87,
             "card":-1,
             "sword":705001
             },
             {
             "startData":
             {
             "chaPos1":207,
             "chaPos2":207,
             "chaPos3":204,
             "chaPos4":208,
             "chaPos5":209,
             "chaPos6":203
             },
             "name":"大战玉田县1",
             "coin":8800,
             "xp":880,
             "type":1,
             "chalevel":88,
             "card":-1,
             "sword":-1
             },
             {
             "startData":
             {
             "chaPos1":207,
             "chaPos2":205,
             "chaPos3":206,
             "chaPos4":207,
             "chaPos5":205,
             "chaPos6":202
             },
             "name":"大战玉田县2",
             "coin":8900,
             "xp":890,
             "type":1,
             "chalevel":89,
             "card":-1,
             "sword":-1
             },
             {
             "startData":
             {
             "chaPos1":207,
             "chaPos2":206,
             "chaPos3":208,
             "chaPos4":210,
             "chaPos5":209,
             "chaPos6":205
             },
             "name":"大战玉田县3",
             "coin":9000,
             "xp":900,
             "type":1,
             "chalevel":90,
             "card":-1,
             "sword":804001
             }
             ]
}